javalang/__init__.py
javalang/ast.py
javalang/javadoc.py
javalang/parse.py
javalang/parser.py
javalang/tokenizer.py
javalang/tree.py
javalang/unparser.py
javalang/util.py
javalang_ext-0.14.3.dist-info/LICENSE.txt
javalang_ext-0.14.3.dist-info/METADATA
javalang_ext-0.14.3.dist-info/WHEEL
javalang_ext-0.14.3.dist-info/top_level.txt
javalang_ext-0.14.3.dist-info/RECORD
