Metadata-Version: 2.1
Name: javalang-ext
Version: 0.14.3
Summary: Pure Python Java parser and tools
Home-page: http://github.com/macnev2013/javalang
Author: Nevil Macwan
Author-email: macnev2013@gmail.com
Classifier: Programming Language :: Python
Classifier: Development Status :: 4 - Beta
Classifier: Operating System :: OS Independent
Classifier: License :: OSI Approved :: MIT License
Classifier: Intended Audience :: Developers
Classifier: Topic :: Software Development :: Libraries
License-File: LICENSE.txt
Requires-Dist: six
